simeeg/__init__.py
simeeg/connectivity.py
simeeg/create_epoch.py
simeeg-0.0.3.3.dist-info/LICENSE
simeeg-0.0.3.3.dist-info/METADATA
simeeg-0.0.3.3.dist-info/WHEEL
simeeg-0.0.3.3.dist-info/top_level.txt
simeeg-0.0.3.3.dist-info/RECORD
